{
  "task": [
    {
      "question": "Which of the following might BEST explain the event accomplished when God creates a new heaven and a new earth? (Rev.21:1) ",
      "time": "30000",
      "choices": [
        {
          "choice": "He annihilates the entire universe and then recreates it from scratch"
        },
        {
          "choice": "He annihilates heaven and earth and then recreates it from scratch"
        },
        {
          "choice": " He dissolves the earth and its atmosphere and then renews it clean and fresh "
        },
        {
          "choice": " He annihilates all of His creation and then recreates it from scratch "
        }
      ],
      "answer": " He dissolves the earth and its atmosphere and then renews it clean and fresh ",
      "type": " City12"
    },
    {
      "question": "New Jerusalem is the eternal city and dwelling place that God has prepared for all those who love Him. (Rev.21:2) ",
      "time": "30000",
      "choices": [
        {
          "choice": "True "
        },
        {
          "choice": "False "
        },
        {
          "choice": ""
        },
        {
          "choice": " "
        }
      ],
      "answer": "True ",
      "type": " City12"
    },
    {
      "question": "Which is a true statement concerning New Jerusalem? (Rev. 21: 3-5)",
      "time": "30000",
      "choices": [
        {
          "choice": "God will dwell there"
        },
        {
          "choice": "There will be no more crying, death, sorrow, nor pain"
        },
        {
          "choice": "His love shall be manifested to us and His glory put upon us"
        },
        {
          "choice": "All of the above"
        }
      ],
      "answer": "All of the above",
      "type": " City12"
    },
    {
      "question": " The existence of both the river of water of life and the tree of life might be an indication that we will be “required” to eat and drink in heaven. (Rev. 22: 1-2) ",
      "time": "30000",
      "choices": [
        {
          "choice": "True"
        },
        {
          "choice": "False"
        },
        {
          "choice": ""
        },
        {
          "choice": ""
        }
      ],
      "answer": "False",
      "type": " City12"
    },
    {
      "question": "Which of the following statements IS NOT true concerning heaven? (Rev. 22: 3-5) ",
      "time": "30000",
      "choices": [
        {
          "choice": "There shall be no more curse"
        },
        {
          "choice": "There shall be no night"
        },
        {
          "choice": "The throne of God and of the Lamb are in it"
        },
        {
          "choice": "There will no longer be a need to serve God"
        }
      ],
      "answer": "There will no longer be a need to serve God",
      "type": " City12"
    },
    {
      "question": "Which of the following BEST explains the “marriage supper of the Lamb”? (Rev. 19 : 9)",
      "time": "30000",
      "choices": [
        {
          "choice": " Blessed are those who are called to the marriage supper"
        },
        {
          "choice": " It will commemorate the marriage between Christ and His Church and the bridal relationship between God"
        },
        {
          "choice": "It will be served on earth during the Millennium"
        },
        {
          "choice": "To explain the evil of marrying one's stepmother"
        }
      ],
      "answer": " It will commemorate the marriage between Christ and His Church and the bridal relationship between God",
      "type": " City12"
    },
    {
      "question": "Which IS NOT included as a reason why heaven explodes into a chorus of gladness and rejoicing to the glory of God? (Rev 19 : 5-8) ",
      "time": "30000",
      "choices": [
        {
          "choice": "The Lord God Omnipotent reigns! "
        },
        {
          "choice": "The marriage of the Lamb has come"
        },
        {
          "choice": "His bride has made herself ready"
        },
        {
          "choice": "None, they all explain the rejoicing and gladness "
        }
      ],
      "answer": "None, they all explain the rejoicing and gladness ",
      "type": " City12"
    },
    {
      "question": "Which of the following IS NOT what John said as he beheld Christ about to leave heaven and return to earth? (Rev. 19:11)",
      "time": "30000",
      "choices": [
        {
          "choice": "He is called Faithful and True."
        },
        {
          "choice": "His robe was white and clean"
        },
        {
          "choice": "His eyes were a flame of fire"
        },
        {
          "choice": "Upon His head were many crowns"
        }
      ],
      "answer": "His robe was white and clean",
      "type": " City12"
    },
    {
      "question": "Which of the following applies to the resurrection? (Rev.  20: 5-6) ",
      "time": "30000",
      "choices": [
        {
          "choice": "Everyone who dies will be resurrected "
        },
        {
          "choice": "The saved will all resurrect before the Millennium "
        },
        {
          "choice": "The unsaved will not resurrect until after the Millennium "
        },
        {
          "choice": "All of the above "
        }
      ],
      "answer": "All of the above ",
      "type": " City12"
    }
  ]
}



  

	

